netzeus_core_config/__init__.py
netzeus_core_config/config.py
netzeus_core_config-0.0.3.dist-info/METADATA
netzeus_core_config-0.0.3.dist-info/WHEEL
netzeus_core_config-0.0.3.dist-info/top_level.txt
netzeus_core_config-0.0.3.dist-info/RECORD
