Metadata-Version: 2.1
Name: netzeus-core-config
Version: 0.0.3
Summary: NetZeus Core Config module for managing configuration data across all microservices/plugins
Author: Brandon Spendlove
Author-email: brandon.spendlove@netzeus.io
Requires-Dist: python-dotenv (==0.21.0)
Requires-Dist: loguru (==0.6.0)
Requires-Dist: pydantic (==1.10.2)
